jobio/__init__.py
jobio/defaults.py
jobio/job.py
jobio/util.py
jobio/cli/__init__.py
jobio/cli/args.py
jobio/cli/cli.py
jobio/cli/helpers.py
jobio/storage/__init__.py
jobio/storage/s3.py
jobio/storage/staging.py
tests/__init__.py
tests/test_cli.py
tests/test_job.py
tests/test_storage.py
jobio-0.0.0a10.dist-info/LICENSE
jobio-0.0.0a10.dist-info/METADATA
jobio-0.0.0a10.dist-info/WHEEL
jobio-0.0.0a10.dist-info/entry_points.txt
jobio-0.0.0a10.dist-info/top_level.txt
jobio-0.0.0a10.dist-info/RECORD
