Metadata-Version: 2.1
Name: jobio
Version: 0.0.0a10
Summary: A bootstrap package to handle input and output data for batch processes
Home-page: https://github.com/rasmunk/jobio
Author: Rasmus Munk
Author-email: munk1@live.dk
License: MIT
Keywords: Job,IO,S3,Batch
Platform: UNKNOWN
Classifier: Intended Audience :: Developers
Classifier: Intended Audience :: System Administrators
Classifier: License :: OSI Approved :: MIT License
Classifier: Programming Language :: Python :: 3.6
Classifier: Programming Language :: Python :: 3.7
Classifier: Programming Language :: Python :: 3.8
Classifier: Programming Language :: Python :: 3.9
Requires-Dist: boto3
Provides-Extra: dev
Requires-Dist: black (==20.8b1) ; extra == 'dev'
Requires-Dist: docutils (==0.16) ; extra == 'dev'
Requires-Dist: flake8 (==3.8.4) ; extra == 'dev'
Provides-Extra: test
Requires-Dist: pytest (==6.1.*) ; extra == 'test'
Requires-Dist: flake8 (==3.8.4) ; extra == 'test'
